log_sender/__init__.py
log_sender/api.py
log_sender/cli.py
log_sender/py.typed
log_sender/senders/exceptions.py
log_sender/senders/telegram_bot_sender.py
log_sender-1.0.1.dist-info/METADATA
log_sender-1.0.1.dist-info/WHEEL
log_sender-1.0.1.dist-info/entry_points.txt
log_sender-1.0.1.dist-info/RECORD
