Metadata-Version: 2.4
Name: log-sender
Version: 1.0.1
Summary: Add your description here
Author-email: Betzabeth Maestre <betzabeth.maestre@micasino.com>, Jesus Bandez <jesus.bandez@mcgroupvenezuela.com>
Requires-Python: >=3.10
Requires-Dist: click>=8.2.0
Requires-Dist: niquests>=3.14.0
